agnm/__init__.py
agnm/motion.py
agnm-1.0.3.dist-info/LICENSE.txt
agnm-1.0.3.dist-info/METADATA
agnm-1.0.3.dist-info/WHEEL
agnm-1.0.3.dist-info/top_level.txt
agnm-1.0.3.dist-info/RECORD
