Metadata-Version: 2.1
Name: agnm
Version: 1.0.3
Summary: A package for physics motion calculations
Author-email: Agnė Moleikaitytė <agnmol@ktu.lt>
Classifier: Programming Language :: Python :: 3
Classifier: License :: OSI Approved :: MIT License
Classifier: Operating System :: OS Independent
Requires-Python: >=3.10
License-File: LICENSE.txt
